{
    "datas": {
        "goods_list": [
            {
                "goods_id": "227209",
                "goods_name": "2019春季新款小白鞋男韩版板鞋男士白鞋百搭休闲鞋夏季增高男鞋子 白色 36",
                "goods_price": "89.00",
                "goods_promotion_price": "89.00",
                "goods_salenum": "1",
                "store_name": "潮男公社",
                "goods_image_url": "https://www.nanshig.com/data/upload/shop/store/goods/47/47_06071111289163602_360.jpg"
            },
            {
                "goods_id": "227182",
                "goods_name": "2019春季透气阿甘鞋男小白鞋男士休闲帆布板鞋韩版潮流男鞋子潮鞋 白黑 36",
                "goods_price": "89.00",
                "goods_promotion_price": "89.00",
                "goods_salenum": "1",
                "store_name": "潮男公社",
                "goods_image_url": "https://www.nanshig.com/data/upload/shop/store/goods/47/47_06071103152844782_360.jpg"
            },
            {
                "goods_id": "227155",
                "goods_name": "2019春季新款小白鞋男士板鞋男韩版潮鞋休闲鞋百搭白鞋男鞋子夏季 白色 36",
                "goods_price": "89.00",
                "goods_promotion_price": "89.00",
                "goods_salenum": "0",
                "store_name": "潮男公社",
                "goods_image_url": "https://www.nanshig.com/data/upload/shop/store/goods/47/47_06071100369195301_360.jpg"
            },
            {
                "goods_id": "227128",
                "goods_name": "2019春季新款小白鞋男鞋子韩版夏季板鞋男士百搭白鞋帆布休闲潮鞋 白色 36",
                "goods_price": "89.00",
                "goods_promotion_price": "89.00",
                "goods_salenum": "0",
                "store_name": "潮男公社",
                "goods_image_url": "https://www.nanshig.com/data/upload/shop/store/goods/47/47_06071097359425992_360.jpg"
            },
            {
                "goods_id": "226885",
                "goods_name": "马丁靴男靴子高帮雪地男鞋冬季中帮短靴潮工装沙漠靴英伦复古百搭 黑色 39",
                "goods_price": "139.00",
                "goods_promotion_price": "139.00",
                "goods_salenum": "1",
                "store_name": "MG鞋店",
                "goods_image_url": "https://www.nanshig.com/data/upload/shop/store/goods/41/41_05967491081317810_360.jpg"
            },
            {
                "goods_id": "226796",
                "goods_name": "秋季新款男鞋子青春潮流男士韩版百搭休闲鞋跑步冬季运动潮鞋 黑色 39",
                "goods_price": "108.00",
                "goods_promotion_price": "108.00",
                "goods_salenum": "0",
                "store_name": "MG鞋店",
                "goods_image_url": "https://www.nanshig.com/data/upload/shop/store/goods/41/41_05961427447152871_360.jpg"
            },
            {
                "goods_id": "226778",
                "goods_name": "冬季新款男鞋高帮鞋韩版潮流百搭ins板鞋运动嘻哈男士潮鞋子 黑色 39",
                "goods_price": "118.00",
                "goods_promotion_price": "118.00",
                "goods_salenum": "0",
                "store_name": "MG鞋店",
                "goods_image_url": "https://www.nanshig.com/data/upload/shop/store/goods/41/41_05961425067072953_360.jpg"
            },
            {
                "goods_id": "226760",
                "goods_name": "冬季新款小白鞋子男韩版潮流休闲鞋学生百搭板鞋运动男士潮鞋 白色 39",
                "goods_price": "108.00",
                "goods_promotion_price": "108.00",
                "goods_salenum": "0",
                "store_name": "MG鞋店",
                "goods_image_url": "https://www.nanshig.com/data/upload/shop/store/goods/41/41_05961421819864549_360.jpg"
            },
            {
                "goods_id": "226742",
                "goods_name": "冬季新款男鞋子男士潮鞋百搭休闲鞋帆布鞋韩版潮运动秋季板鞋 黑色 39",
                "goods_price": "89.00",
                "goods_promotion_price": "89.00",
                "goods_salenum": "0",
                "store_name": "MG鞋店",
                "goods_image_url": "https://www.nanshig.com/data/upload/shop/store/goods/41/41_05961416965050308_360.jpg"
            },
            {
                "goods_id": "226649",
                "goods_name": "潮男鞋秋冬季新款男士高帮鞋男百搭休闲板鞋内增高街舞鞋8CM黑白马丁靴 白色 39",
                "goods_price": "112.00",
                "goods_promotion_price": "112.00",
                "goods_salenum": "1",
                "store_name": "寻优鞋品",
                "goods_image_url": "https://www.nanshig.com/data/upload/shop/store/goods/42/42_05943354852362407_360.jpg"
            },
            {
                "goods_id": "226643",
                "goods_name": "潮男鞋百搭潮鞋小白鞋高帮休闲鞋青少年运动学生板鞋6CM内增高男鞋8公分 白色 39",
                "goods_price": "106.00",
                "goods_promotion_price": "106.00",
                "goods_salenum": "0",
                "store_name": "寻优鞋品",
                "goods_image_url": "https://www.nanshig.com/data/upload/shop/store/goods/42/42_05943353450158107_360.jpg"
            },
            {
                "goods_id": "226631",
                "goods_name": "潮男鞋2018冬季新款保暖加绒棉鞋加厚韩版百搭学生休闲高帮男鞋冬天冬鞋 白黑 39",
                "goods_price": "98.00",
                "goods_promotion_price": "98.00",
                "goods_salenum": "0",
                "store_name": "寻优鞋品",
                "goods_image_url": "https://www.nanshig.com/data/upload/shop/store/goods/42/42_05943350610168912_360.jpg"
            },
            {
                "goods_id": "226619",
                "goods_name": "潮男鞋秋冬季高帮板鞋男鞋时尚百搭潮鞋韩版英伦潮流休闲运动鞋小白鞋潮 白灰 39",
                "goods_price": "109.00",
                "goods_promotion_price": "109.00",
                "goods_salenum": "0",
                "store_name": "寻优鞋品",
                "goods_image_url": "https://www.nanshig.com/data/upload/shop/store/goods/42/42_05943346593585111_360.jpg"
            },
            {
                "goods_id": "226613",
                "goods_name": "潮男鞋高帮鞋板鞋韩版潮流百搭秋季厚底内增高小白鞋情侣休闲运动男鞋子 白色 39",
                "goods_price": "108.00",
                "goods_promotion_price": "108.00",
                "goods_salenum": "1",
                "store_name": "寻优鞋品",
                "goods_image_url": "https://www.nanshig.com/data/upload/shop/store/goods/42/42_05943344220891470_360.jpg"
            },
            {
                "goods_id": "226595",
                "goods_name": "潮男鞋秋季高帮鞋男鞋韩版百搭情侣鞋2018新款内增高小白鞋青年社会板鞋 白蓝红 39",
                "goods_price": "118.00",
                "goods_promotion_price": "118.00",
                "goods_salenum": "0",
                "store_name": "寻优鞋品",
                "goods_image_url": "https://www.nanshig.com/data/upload/shop/store/goods/42/42_05943341565702315_360.jpg"
            },
            {
                "goods_id": "226577",
                "goods_name": "型男小白鞋男鞋韩版潮流男士休闲鞋秋季学生板鞋透气潮鞋子 黑色 39",
                "goods_price": "89.00",
                "goods_promotion_price": "89.00",
                "goods_salenum": "1",
                "store_name": "MG鞋店",
                "goods_image_url": "https://www.nanshig.com/data/upload/shop/store/goods/41/41_05935729896473188_360.jpg"
            },
            {
                "goods_id": "226559",
                "goods_name": "型男男鞋秋季透气潮鞋男士休闲鞋子韩版皮鞋百搭小白鞋男学生白色板鞋 黑色 39",
                "goods_price": "118.00",
                "goods_promotion_price": "118.00",
                "goods_salenum": "0",
                "store_name": "MG鞋店",
                "goods_image_url": "https://www.nanshig.com/data/upload/shop/store/goods/41/41_05935726575997926_360.jpg"
            },
            {
                "goods_id": "226541",
                "goods_name": "型男鞋子男秋季透气板鞋韩版潮流百搭帆布鞋休闲布鞋学生鞋男 黑色 39",
                "goods_price": "125.00",
                "goods_promotion_price": "125.00",
                "goods_salenum": "0",
                "store_name": "MG鞋店",
                "goods_image_url": "https://www.nanshig.com/data/upload/shop/store/goods/41/41_05935723458911946_360.jpg"
            },
            {
                "goods_id": "226523",
                "goods_name": "型男鞋子男2018秋季新款韩版潮流高帮帆布鞋休闲潮鞋冬季男士百搭板鞋 黑色 39",
                "goods_price": "118.00",
                "goods_promotion_price": "118.00",
                "goods_salenum": "1",
                "store_name": "MG鞋店",
                "goods_image_url": "https://www.nanshig.com/data/upload/shop/store/goods/41/41_05935721004763216_360.jpg"
            },
            {
                "goods_id": "226334",
                "goods_name": "男鞋冬季2018新款高帮帆布鞋韩版潮流港风鞋子男百搭板鞋休闲潮鞋 黑白 39",
                "goods_price": "89.00",
                "goods_promotion_price": "89.00",
                "goods_salenum": "0",
                "store_name": "寻优鞋品",
                "goods_image_url": "https://www.nanshig.com/data/upload/shop/store/goods/42/42_05922705301897792_360.jpg"
            }, {
                "goods_id": "227209",
                "goods_name": "2019春季新款小白鞋男韩版板鞋男士白鞋百搭休闲鞋夏季增高男鞋子 白色 36",
                "goods_price": "89.00",
                "goods_promotion_price": "89.00",
                "goods_salenum": "1",
                "store_name": "潮男公社",
                "goods_image_url": "https://www.nanshig.com/data/upload/shop/store/goods/47/47_06071111289163602_360.jpg"
            },
            {
                "goods_id": "227182",
                "goods_name": "2019春季透气阿甘鞋男小白鞋男士休闲帆布板鞋韩版潮流男鞋子潮鞋 白黑 36",
                "goods_price": "89.00",
                "goods_promotion_price": "89.00",
                "goods_salenum": "1",
                "store_name": "潮男公社",
                "goods_image_url": "https://www.nanshig.com/data/upload/shop/store/goods/47/47_06071103152844782_360.jpg"
            },
            {
                "goods_id": "227155",
                "goods_name": "2019春季新款小白鞋男士板鞋男韩版潮鞋休闲鞋百搭白鞋男鞋子夏季 白色 36",
                "goods_price": "89.00",
                "goods_promotion_price": "89.00",
                "goods_salenum": "0",
                "store_name": "潮男公社",
                "goods_image_url": "https://www.nanshig.com/data/upload/shop/store/goods/47/47_06071100369195301_360.jpg"
            },
            {
                "goods_id": "227128",
                "goods_name": "2019春季新款小白鞋男鞋子韩版夏季板鞋男士百搭白鞋帆布休闲潮鞋 白色 36",
                "goods_price": "89.00",
                "goods_promotion_price": "89.00",
                "goods_salenum": "0",
                "store_name": "潮男公社",
                "goods_image_url": "https://www.nanshig.com/data/upload/shop/store/goods/47/47_06071097359425992_360.jpg"
            },
            {
                "goods_id": "226885",
                "goods_name": "马丁靴男靴子高帮雪地男鞋冬季中帮短靴潮工装沙漠靴英伦复古百搭 黑色 39",
                "goods_price": "139.00",
                "goods_promotion_price": "139.00",
                "goods_salenum": "1",
                "store_name": "MG鞋店",
                "goods_image_url": "https://www.nanshig.com/data/upload/shop/store/goods/41/41_05967491081317810_360.jpg"
            },
            {
                "goods_id": "226796",
                "goods_name": "秋季新款男鞋子青春潮流男士韩版百搭休闲鞋跑步冬季运动潮鞋 黑色 39",
                "goods_price": "108.00",
                "goods_promotion_price": "108.00",
                "goods_salenum": "0",
                "store_name": "MG鞋店",
                "goods_image_url": "https://www.nanshig.com/data/upload/shop/store/goods/41/41_05961427447152871_360.jpg"
            },
            {
                "goods_id": "226778",
                "goods_name": "冬季新款男鞋高帮鞋韩版潮流百搭ins板鞋运动嘻哈男士潮鞋子 黑色 39",
                "goods_price": "118.00",
                "goods_promotion_price": "118.00",
                "goods_salenum": "0",
                "store_name": "MG鞋店",
                "goods_image_url": "https://www.nanshig.com/data/upload/shop/store/goods/41/41_05961425067072953_360.jpg"
            },
            {
                "goods_id": "226760",
                "goods_name": "冬季新款小白鞋子男韩版潮流休闲鞋学生百搭板鞋运动男士潮鞋 白色 39",
                "goods_price": "108.00",
                "goods_promotion_price": "108.00",
                "goods_salenum": "0",
                "store_name": "MG鞋店",
                "goods_image_url": "https://www.nanshig.com/data/upload/shop/store/goods/41/41_05961421819864549_360.jpg"
            },
            {
                "goods_id": "226742",
                "goods_name": "冬季新款男鞋子男士潮鞋百搭休闲鞋帆布鞋韩版潮运动秋季板鞋 黑色 39",
                "goods_price": "89.00",
                "goods_promotion_price": "89.00",
                "goods_salenum": "0",
                "store_name": "MG鞋店",
                "goods_image_url": "https://www.nanshig.com/data/upload/shop/store/goods/41/41_05961416965050308_360.jpg"
            },
            {
                "goods_id": "226649",
                "goods_name": "潮男鞋秋冬季新款男士高帮鞋男百搭休闲板鞋内增高街舞鞋8CM黑白马丁靴 白色 39",
                "goods_price": "112.00",
                "goods_promotion_price": "112.00",
                "goods_salenum": "1",
                "store_name": "寻优鞋品",
                "goods_image_url": "https://www.nanshig.com/data/upload/shop/store/goods/42/42_05943354852362407_360.jpg"
            },
            {
                "goods_id": "226643",
                "goods_name": "潮男鞋百搭潮鞋小白鞋高帮休闲鞋青少年运动学生板鞋6CM内增高男鞋8公分 白色 39",
                "goods_price": "106.00",
                "goods_promotion_price": "106.00",
                "goods_salenum": "0",
                "store_name": "寻优鞋品",
                "goods_image_url": "https://www.nanshig.com/data/upload/shop/store/goods/42/42_05943353450158107_360.jpg"
            },
            {
                "goods_id": "226631",
                "goods_name": "潮男鞋2018冬季新款保暖加绒棉鞋加厚韩版百搭学生休闲高帮男鞋冬天冬鞋 白黑 39",
                "goods_price": "98.00",
                "goods_promotion_price": "98.00",
                "goods_salenum": "0",
                "store_name": "寻优鞋品",
                "goods_image_url": "https://www.nanshig.com/data/upload/shop/store/goods/42/42_05943350610168912_360.jpg"
            },
            {
                "goods_id": "226619",
                "goods_name": "潮男鞋秋冬季高帮板鞋男鞋时尚百搭潮鞋韩版英伦潮流休闲运动鞋小白鞋潮 白灰 39",
                "goods_price": "109.00",
                "goods_promotion_price": "109.00",
                "goods_salenum": "0",
                "store_name": "寻优鞋品",
                "goods_image_url": "https://www.nanshig.com/data/upload/shop/store/goods/42/42_05943346593585111_360.jpg"
            },
            {
                "goods_id": "226613",
                "goods_name": "潮男鞋高帮鞋板鞋韩版潮流百搭秋季厚底内增高小白鞋情侣休闲运动男鞋子 白色 39",
                "goods_price": "108.00",
                "goods_promotion_price": "108.00",
                "goods_salenum": "1",
                "store_name": "寻优鞋品",
                "goods_image_url": "https://www.nanshig.com/data/upload/shop/store/goods/42/42_05943344220891470_360.jpg"
            },
            {
                "goods_id": "226595",
                "goods_name": "潮男鞋秋季高帮鞋男鞋韩版百搭情侣鞋2018新款内增高小白鞋青年社会板鞋 白蓝红 39",
                "goods_price": "118.00",
                "goods_promotion_price": "118.00",
                "goods_salenum": "0",
                "store_name": "寻优鞋品",
                "goods_image_url": "https://www.nanshig.com/data/upload/shop/store/goods/42/42_05943341565702315_360.jpg"
            },
            {
                "goods_id": "226577",
                "goods_name": "型男小白鞋男鞋韩版潮流男士休闲鞋秋季学生板鞋透气潮鞋子 黑色 39",
                "goods_price": "89.00",
                "goods_promotion_price": "89.00",
                "goods_salenum": "1",
                "store_name": "MG鞋店",
                "goods_image_url": "https://www.nanshig.com/data/upload/shop/store/goods/41/41_05935729896473188_360.jpg"
            },
            {
                "goods_id": "226559",
                "goods_name": "型男男鞋秋季透气潮鞋男士休闲鞋子韩版皮鞋百搭小白鞋男学生白色板鞋 黑色 39",
                "goods_price": "118.00",
                "goods_promotion_price": "118.00",
                "goods_salenum": "0",
                "store_name": "MG鞋店",
                "goods_image_url": "https://www.nanshig.com/data/upload/shop/store/goods/41/41_05935726575997926_360.jpg"
            },
            {
                "goods_id": "226541",
                "goods_name": "型男鞋子男秋季透气板鞋韩版潮流百搭帆布鞋休闲布鞋学生鞋男 黑色 39",
                "goods_price": "125.00",
                "goods_promotion_price": "125.00",
                "goods_salenum": "0",
                "store_name": "MG鞋店",
                "goods_image_url": "https://www.nanshig.com/data/upload/shop/store/goods/41/41_05935723458911946_360.jpg"
            },
            {
                "goods_id": "226523",
                "goods_name": "型男鞋子男2018秋季新款韩版潮流高帮帆布鞋休闲潮鞋冬季男士百搭板鞋 黑色 39",
                "goods_price": "118.00",
                "goods_promotion_price": "118.00",
                "goods_salenum": "1",
                "store_name": "MG鞋店",
                "goods_image_url": "https://www.nanshig.com/data/upload/shop/store/goods/41/41_05935721004763216_360.jpg"
            },
            {
                "goods_id": "226334",
                "goods_name": "男鞋冬季2018新款高帮帆布鞋韩版潮流港风鞋子男百搭板鞋休闲潮鞋 黑白 39",
                "goods_price": "89.00",
                "goods_promotion_price": "89.00",
                "goods_salenum": "0",
                "store_name": "寻优鞋品",
                "goods_image_url": "https://www.nanshig.com/data/upload/shop/store/goods/42/42_05922705301897792_360.jpg"
            }
        ]
    }
}